gans_eval/__init__.py
gans_eval/dataset.py
gans_eval/extractor.py
gans_eval/inception.py
gans_eval/main.py
gans_eval/metrics.py
gans_eval/utils.py
gans_eval-0.0.5.dist-info/LICENSE.txt
gans_eval-0.0.5.dist-info/METADATA
gans_eval-0.0.5.dist-info/WHEEL
gans_eval-0.0.5.dist-info/entry_points.txt
gans_eval-0.0.5.dist-info/top_level.txt
gans_eval-0.0.5.dist-info/RECORD
