Metadata-Version: 2.1
Name: gans-eval
Version: 0.0.5
Summary: This package provides measurement tools for Generative Adversarial Networks (GANs), including Inception Score (IS), Fréchet Inception Distance (FID), Kernel Inception Distance (KID), and Precision and Recall (PR). These metrics are used to evaluate the quality and diversity of generated images in GANs. The package streamlines the use of these metrics, making it easier to apply them to your work.
Home-page: https://github.com/GiangHLe/gans-evals
Author: Giang Le
Author-email: lhgiang149@gmail.com
Classifier: Programming Language :: Python :: 3
Classifier: Intended Audience :: Science/Research
Classifier: License :: OSI Approved :: MIT License
Classifier: Operating System :: POSIX :: Linux
Classifier: Programming Language :: Python :: 3
Requires-Python: >=3.6
License-File: LICENSE.txt
Requires-Dist: numpy
Requires-Dist: opencv-python
Requires-Dist: pillow
Requires-Dist: scipy
Requires-Dist: tqdm
Requires-Dist: timm
Requires-Dist: torch >=1.7.0
Requires-Dist: torchvision >=0.8.0
